example.py
example_package_dhruvsaraiya/__init__.py
example_package_dhruvsaraiya-0.0.3.dist-info/LICENSE
example_package_dhruvsaraiya-0.0.3.dist-info/METADATA
example_package_dhruvsaraiya-0.0.3.dist-info/WHEEL
example_package_dhruvsaraiya-0.0.3.dist-info/top_level.txt
example_package_dhruvsaraiya-0.0.3.dist-info/RECORD
